me_mover-3.2.3.dist-info/licenses/LICENSE
memover/__init__.py
memover/__main__.py
memover/arguments_parser.py
memover/episode_mover.py
memover/file_handler.py
memover/file_matcher.py
memover/language_codes.py
memover/logger.py
memover/main.py
memover/media_file_extractor.py
memover/mover.py
memover/movie_mover.py
memover/show_name_extractor.py
memover/subtitles.py
memover/watcher/__init__.py
memover/watcher/async_watcher.py
memover/watcher/path_queue.py
memover/watcher/synced_watcher.py
me_mover-3.2.3.dist-info/METADATA
me_mover-3.2.3.dist-info/WHEEL
me_mover-3.2.3.dist-info/entry_points.txt
me_mover-3.2.3.dist-info/top_level.txt
me_mover-3.2.3.dist-info/RECORD
