Metadata-Version: 2.4
Name: me-mover
Version: 3.2.3
Summary: Organize movies and tv-shows
Author: Alexander Berlind
License-Expression: MIT
Project-URL: Homepage, https://github.com/Alecktos/me-mover.git
Requires-Python: >=3.14
License-File: LICENSE
Requires-Dist: watchdog==6.0.0
Provides-Extra: dev
Requires-Dist: flake8==7.0.0; extra == "dev"
Dynamic: license-file
